{
  "parent": "item/generated",
  "textures": {
    "layer0": "zeldamod:item/blue_emerald"},

  "display": {
    "thirdperson_righthand": {
      "rotation": [ 0, 90, 0 ],
      "translation": [ 0, 0, 0 ],
      "scale": [ 1, 1, 1 ]
    },
    "thirdperson_lefthand": {
      "rotation": [ 0, 90, 0 ],
      "translation": [ 1.2, 2, 2 ],
      "scale": [ 1, 1, 1 ]
    },
    "firstperson_righthand": {
      "rotation": [ 0, 180, 5 ],
      "translation": [ -10, 2, -10 ],
      "scale": [ 1.25, 1.25, 1.25 ]
    },
    "firstperson_lefthand": {
      "rotation": [ 0, 180, 5 ],
      "translation": [ 10, 0, -10 ],
      "scale": [ 1.25, 1.25, 1.25 ]

    },
    "fixed": {
      "rotation": [ 0, 180, 0 ],
      "translation": [ 0, 0, 0],
      "scale":[ 0.55, 0.55, 0.55]
    },
    "ground": {
      "rotation": [ 0, 0, 0 ],
      "translation": [ 0, 0, 0],
      "scale":[ 0.25, 0.25, 0.25]
    },



    "overrides": [
      {
        "predicate": {
          "minecraft:blocking": 1
        },

        "model": "zeldamod:item/deku_shield_blocking" }
      ]}}
